tfhub_esrgan_wrapper/__init__.py
tfhub_esrgan_wrapper/hubFnc.py
tfhub_esrgan_wrapper/imgFunc.py
tfhub_esrgan_wrapper/tensorFnc.py
tfhub_esrgan_wrapper-1.0.0.dist-info/METADATA
tfhub_esrgan_wrapper-1.0.0.dist-info/WHEEL
tfhub_esrgan_wrapper-1.0.0.dist-info/top_level.txt
tfhub_esrgan_wrapper-1.0.0.dist-info/RECORD
