Metadata-Version: 2.1
Name: tfhub-esrgan-wrapper
Version: 1.0.0
Summary: A wrapper that contains quick functions to load and process data with Googles TF Hub ESRGAN model
Home-page: https://github.com/alex-parisi/tfhub-esrgan-wrapper
Author: Alex Parisi
Author-email: alex.parisi@outlook.com
License: UNKNOWN
Project-URL: Bug Tracker, https://github.com/alex-parisi/tfhub-esrgan-wrapper/issues
Platform: UNKNOWN
Classifier: Programming Language :: Python :: 3
Classifier: License :: OSI Approved :: MIT License
Classifier: Operating System :: OS Independent
Requires-Python: >=3.7
Requires-Dist: tensorflow (==2.7.0)
Requires-Dist: tensorflow-hub (==0.12.0)
Requires-Dist: matplotlib (==3.5.1)
Requires-Dist: Pillow (==9.0.0)
Requires-Dist: numpy (==1.21.5)
